klinear.py
klinear-0.5.6.dist-info/METADATA
klinear-0.5.6.dist-info/WHEEL
klinear-0.5.6.dist-info/top_level.txt
klinear-0.5.6.dist-info/RECORD
