Metadata-Version: 2.1
Name: klinear
Version: 0.5.6
Requires-Dist: requests
